{
  "title": "",
  "teams":{
    "left": "",
    "right": ""
  },
  "surveys":[
    {
      "id": 1,
      "title": "Name a reason you might get rid of an old family heirloom.",
      "answers":[
        {
          "value": "BROKEN",
          "points": 20
        },{
          "value": "UGLY",
          "points": 22
        },{
          "value": "DIVORCE",
          "points": 18
        },{
          "value": "SELL / NEED MONEY",
          "points": 12
        },{
          "value": "TOO MUCH STUFF",
          "points": 10
        },{
          "value": "FAMILY FEUD",
          "points": 5
        },{
          "value": "MOVING",
          "points": 2
        }
      ]
    },{
      "id": 2,
      "title": "What are you most afraid of?",
      "answers":[
        {
          "value": "CLOWNS",
          "points": 28
        },{
          "value": "SPIDERS",
          "points": 25
        },{
          "value": "SNAKES",
          "points": 17
        },{
          "value": "GHOSTS",
          "points": 15
        },{
          "value": "HEIGHTS",
          "points": 14
        },{
          "value": "NIGHTMAN",
          "points": 1
        }
      ]
    },{
      "id": 3,
      "title": "Tell me something many people do just once a week.",
      "answers":[
        {
          "value": "Church",
          "points": 35
        },{
          "value": "Groceries / Shopping",
          "points": 24
        },{
          "value": "Laundry",
          "points": 15
        },{
          "value": "Clean House",
          "points": 9
        }
      ]
    }
  ]
}